serium/__init__.py
serium/caseclasses.py
serium/cc_exceptions.py
serium/types.py
serium-0.1.10.dist-info/DESCRIPTION.rst
serium-0.1.10.dist-info/METADATA
serium-0.1.10.dist-info/RECORD
serium-0.1.10.dist-info/WHEEL
serium-0.1.10.dist-info/metadata.json
serium-0.1.10.dist-info/top_level.txt
