Metadata-Version: 2.0
Name: serium
Version: 0.1.10
Summary: Sustainable case-class serialization library
Home-page: https://github.com/harelba/serium
Author: Harel Ben-Attia
Author-email: harelba@gmail.com
License: MIT
Download-URL: https://github.com/harelba/serium/archive/0.1.10.tar.gz
Keywords: serium case-classes serialization data-migration data-structures strict-typing schema-evolution schema
Platform: UNKNOWN
Classifier: Development Status :: 3 - Alpha
Classifier: Intended Audience :: Developers
Classifier: Topic :: Software Development :: Libraries :: Python Modules
Classifier: License :: OSI Approved :: Apache Software License
Classifier: Programming Language :: Python :: 2
Classifier: Programming Language :: Python :: 2.6
Classifier: Programming Language :: Python :: 2.7
Classifier: Programming Language :: Python :: 2 :: Only
Requires-Python: >=2.6,<3
Provides-Extra: dev
Requires-Dist: pytest; extra == 'dev'
Provides-Extra: test
Requires-Dist: pytest; extra == 'test'
